fileez/__init__.py
fileez/core.py
fileez/version.py
fileez-0.1.0.dist-info/licenses/LICENSE
fileez-0.1.0.dist-info/METADATA
fileez-0.1.0.dist-info/WHEEL
fileez-0.1.0.dist-info/top_level.txt
fileez-0.1.0.dist-info/RECORD
