Metadata-Version: 2.4
Name: fileez
Version: 0.1.0
Summary: A simple and friendly Python library to handle files and folders
Home-page: https://github.com/Rasa8877/fileez
Author: Rasa Dariush
Author-email: letperhut@gmail.com
Classifier: Programming Language :: Python :: 3
Classifier: License :: OSI Approved :: MIT License
Classifier: Operating System :: OS Independent
Requires-Python: >=3.7
License-File: LICENSE
Dynamic: author
Dynamic: author-email
Dynamic: classifier
Dynamic: description
Dynamic: description-content-type
Dynamic: home-page
Dynamic: license-file
Dynamic: requires-python
Dynamic: summary
